{
  "id": "navigation",
  "label": "Navigation",
  "repeatable": false,
  "status": true,
  "json": {
    "Main": {
      "title": {
        "type": "Text",
        "config": {
          "label": "Title",
          "placeholder": ""
        }
      },
      "work_title": {
        "type": "Text",
        "config": {
          "label": "Work Title",
          "placeholder": ""
        }
      },
      "about_title": {
        "type": "Text",
        "config": {
          "label": "About Title",
          "placeholder": ""
        }
      },
      "contact_title": {
        "type": "Text",
        "config": {
          "label": "Contact Title",
          "placeholder": ""
        }
      }
    }
  }
}
